{"Constituency": {"countInfo": {"Valid_Poll": "", "Number_Of_Seats": "5", "Total_Poll": "", "Voting_Age_Pop": "70652", "Quota": "", "Constituency_Name": "East Antrim", "Constituency_Number": "1", "Total_Electorate": "62933", "Spoiled": ""},
"countGroup": [{
    "Candidate_First_Pref_Votes": "", 
    "Status": "", 
    "Occurred_On_Count": "", 
    "Surname": "Beggs", 
    "Firstname": "Roy", 
    "Constituency_Number": "1", 
    "Party_Name": "Ulster Unionist Party", 
    "Candidate_Id": "7132", 
    "Count_Number": "1", 
    "Transfers": "0", 
    "id": 0, 
    "Total_Votes": ""
},
{
    "Candidate_First_Pref_Votes": "", 
    "Status": "", 
    "Occurred_On_Count": "", 
    "Surname": "Best", 
    "Firstname": "Ricky", 
    "Constituency_Number": "1", 
    "Party_Name": "Independent", 
    "Candidate_Id": "19741", 
    "Count_Number": "1", 
    "Transfers": "0", 
    "id": 1, 
    "Total_Votes": ""
},
{
    "Candidate_First_Pref_Votes": "", 
    "Status": "", 
    "Occurred_On_Count": "", 
    "Surname": "Dickson", 
    "Firstname": "Stewart", 
    "Constituency_Number": "1", 
    "Party_Name": "Alliance Party", 
    "Candidate_Id": "4591", 
    "Count_Number": "1", 
    "Transfers": "0", 
    "id": 2, 
    "Total_Votes": ""
},
{
    "Candidate_First_Pref_Votes": "", 
    "Status": "", 
    "Occurred_On_Count": "", 
    "Surname": "Donnelly", 
    "Firstname": "Danny", 
    "Constituency_Number": "1", 
    "Party_Name": "Alliance Party", 
    "Candidate_Id": "9805", 
    "Count_Number": "1", 
    "Transfers": "0", 
    "id": 3, 
    "Total_Votes": ""
},
{
    "Candidate_First_Pref_Votes": "", 
    "Status": "", 
    "Occurred_On_Count": "", 
    "Surname": "Dunlop", 
    "Firstname": "Alan", 
    "Constituency_Number": "1", 
    "Party_Name": "NI Conservatives", 
    "Candidate_Id": "6991", 
    "Count_Number": "1", 
    "Transfers": "0", 
    "id": 4, 
    "Total_Votes": ""
},
{
    "Candidate_First_Pref_Votes": "", 
    "Status": "", 
    "Occurred_On_Count": "", 
    "Surname": "Hilditch", 
    "Firstname": "David", 
    "Constituency_Number": "1", 
    "Party_Name": "Democratic Unionist Party", 
    "Candidate_Id": "11447", 
    "Count_Number": "1", 
    "Transfers": "0", 
    "id": 5, 
    "Total_Votes": ""
},
{
    "Candidate_First_Pref_Votes": "", 
    "Status": "", 
    "Occurred_On_Count": "", 
    "Surname": "Jordan", 
    "Firstname": "Noel", 
    "Constituency_Number": "1", 
    "Party_Name": "UK Independence Party", 
    "Candidate_Id": "6399", 
    "Count_Number": "1", 
    "Transfers": "0", 
    "id": 6, 
    "Total_Votes": ""
},
{
    "Candidate_First_Pref_Votes": "", 
    "Status": "", 
    "Occurred_On_Count": "", 
    "Surname": "Lyons", 
    "Firstname": "Gordon", 
    "Constituency_Number": "1", 
    "Party_Name": "Democratic Unionist Party", 
    "Candidate_Id": "11448", 
    "Count_Number": "1", 
    "Transfers": "0", 
    "id": 7, 
    "Total_Votes": ""
},
{
    "Candidate_First_Pref_Votes": "", 
    "Status": "", 
    "Occurred_On_Count": "", 
    "Surname": "McKillop", 
    "Firstname": "Margaret Anne", 
    "Constituency_Number": "1", 
    "Party_Name": "Social Democratic and Labour Party", 
    "Candidate_Id": "5389", 
    "Count_Number": "1", 
    "Transfers": "0", 
    "id": 8, 
    "Total_Votes": ""
},
{
    "Candidate_First_Pref_Votes": "", 
    "Status": "", 
    "Occurred_On_Count": "", 
    "Surname": "McMullan", 
    "Firstname": "Oliver", 
    "Constituency_Number": "1", 
    "Party_Name": "Sinn Fein", 
    "Candidate_Id": "1061", 
    "Count_Number": "1", 
    "Transfers": "0", 
    "id": 9, 
    "Total_Votes": ""
},
{
    "Candidate_First_Pref_Votes": "", 
    "Status": "", 
    "Occurred_On_Count": "", 
    "Surname": "Patterson", 
    "Firstname": "Dawn", 
    "Constituency_Number": "1", 
    "Party_Name": "Green Party", 
    "Candidate_Id": "10293", 
    "Count_Number": "1", 
    "Transfers": "0", 
    "id": 10, 
    "Total_Votes": ""
},
{
    "Candidate_First_Pref_Votes": "", 
    "Status": "", 
    "Occurred_On_Count": "", 
    "Surname": "Ross", 
    "Firstname": "Stephen", 
    "Constituency_Number": "1", 
    "Party_Name": "Democratic Unionist Party", 
    "Candidate_Id": "19685", 
    "Count_Number": "1", 
    "Transfers": "0", 
    "id": 11, 
    "Total_Votes": ""
},
{
    "Candidate_First_Pref_Votes": "", 
    "Status": "", 
    "Occurred_On_Count": "", 
    "Surname": "Sheridan", 
    "Firstname": "Conor", 
    "Constituency_Number": "1", 
    "Party_Name": "Cross-Community Labour Alternative", 
    "Candidate_Id": "11450", 
    "Count_Number": "1", 
    "Transfers": "0", 
    "id": 12, 
    "Total_Votes": ""
},
{
    "Candidate_First_Pref_Votes": "", 
    "Status": "", 
    "Occurred_On_Count": "", 
    "Surname": "Stewart", 
    "Firstname": "John", 
    "Constituency_Number": "1", 
    "Party_Name": "Ulster Unionist Party", 
    "Candidate_Id": "8121", 
    "Count_Number": "1", 
    "Transfers": "0", 
    "id": 13, 
    "Total_Votes": ""
},
{
    "Candidate_First_Pref_Votes": "", 
    "Status": "", 
    "Occurred_On_Count": "", 
    "Surname": "Wilson", 
    "Firstname": "Ruth", 
    "Constituency_Number": "1", 
    "Party_Name": "Traditional Unionist Voice", 
    "Candidate_Id": "6985", 
    "Count_Number": "1", 
    "Transfers": "0", 
    "id": 14, 
    "Total_Votes": ""
}
]}}
